.DS_Store
jupyterthemes/__init__.py
jupyterthemes/jtplot.py
jupyterthemes/stylefx.py
jupyterthemes/defaults/custom.css
jupyterthemes/defaults/custom.js
jupyterthemes/fonts/monospace/anka-coder/anka-coder-italic.ttf
jupyterthemes/fonts/monospace/anka-coder/anka-coder.ttf
jupyterthemes/fonts/monospace/anka-coder/license.txt
jupyterthemes/fonts/monospace/anonymous-pro/anonymous-pro-italic.ttf
jupyterthemes/fonts/monospace/anonymous-pro/anonymous-pro.ttf
jupyterthemes/fonts/monospace/anonymous-pro/license.txt
jupyterthemes/fonts/monospace/aurulent/aurulent.otf
jupyterthemes/fonts/monospace/aurulent/license.txt
jupyterthemes/fonts/monospace/bitstream-vera/bitstream-vera-italic.woff
jupyterthemes/fonts/monospace/bitstream-vera/bitstream-vera.woff
jupyterthemes/fonts/monospace/bitstream-vera/license.txt
jupyterthemes/fonts/monospace/bpmono/bpmono-italic.woff
jupyterthemes/fonts/monospace/bpmono/bpmono.woff
jupyterthemes/fonts/monospace/bpmono/license.txt
jupyterthemes/fonts/monospace/code-new-roman/code-new-roman.otf
jupyterthemes/fonts/monospace/consolamono/consolamono.ttf
jupyterthemes/fonts/monospace/consolamono/license.txt
jupyterthemes/fonts/monospace/cousine/cousine-italic.ttf
jupyterthemes/fonts/monospace/cousine/cousine.ttf
jupyterthemes/fonts/monospace/cousine/license.txt
jupyterthemes/fonts/monospace/dejavu/dejavu-italic.ttf
jupyterthemes/fonts/monospace/dejavu/dejavu.ttf
jupyterthemes/fonts/monospace/dejavu/license.txt
jupyterthemes/fonts/monospace/droidmono/droid-sans-mono.woff
jupyterthemes/fonts/monospace/droidmono/license.txt
jupyterthemes/fonts/monospace/fira/fira.ttf
jupyterthemes/fonts/monospace/fira/license.txt
jupyterthemes/fonts/monospace/firacode/firacode.otf
jupyterthemes/fonts/monospace/generic/generic.otf
jupyterthemes/fonts/monospace/generic/license.txt
jupyterthemes/fonts/monospace/hack/Hack-Italic.ttf
jupyterthemes/fonts/monospace/hack/hack-italic.woff2
jupyterthemes/fonts/monospace/hack/hack.ttf
jupyterthemes-0.19.6.dist-info/DESCRIPTION.rst
jupyterthemes-0.19.6.dist-info/METADATA
jupyterthemes-0.19.6.dist-info/RECORD
jupyterthemes-0.19.6.dist-info/WHEEL
jupyterthemes-0.19.6.dist-info/entry_points.txt
jupyterthemes-0.19.6.dist-info/metadata.json
jupyterthemes-0.19.6.dist-info/top_level.txt
